pymasker.py
setup.py
pymasker.egg-info/PKG-INFO
pymasker.egg-info/SOURCES.txt
pymasker.egg-info/dependency_links.txt
pymasker.egg-info/entry_points.txt
pymasker.egg-info/not-zip-safe
pymasker.egg-info/requires.txt
pymasker.egg-info/top_level.txt