Metadata-Version: 1.0
Name: pymasker
Version: 0.3.2
Summary: python package for mask generation from landsat 8 Quality Assessment band and MODIS land products.
Home-page: https://github.com/haoliangyu/pymasker
Author: Haoliang Yu
Author-email: haoliang.yu@outlook.com
License: MIT
Platform: UNKNOWN
